deprecation.py
libdeprecation-1.0.dist-info/DESCRIPTION.rst
libdeprecation-1.0.dist-info/METADATA
libdeprecation-1.0.dist-info/RECORD
libdeprecation-1.0.dist-info/WHEEL
libdeprecation-1.0.dist-info/metadata.json
libdeprecation-1.0.dist-info/top_level.txt
